raincolor/__init__.py
raincolor/color.py
raincolor/themes.py
raincolor/utils.py
raincolor-0.1.4.dist-info/LICENSE
raincolor-0.1.4.dist-info/METADATA
raincolor-0.1.4.dist-info/WHEEL
raincolor-0.1.4.dist-info/top_level.txt
raincolor-0.1.4.dist-info/RECORD
